aistack/__init__.py
aistack/__main__.py
aistack/cli.py
aistack/version.py
aistack-0.0.1.dist-info/METADATA
aistack-0.0.1.dist-info/WHEEL
aistack-0.0.1.dist-info/top_level.txt
aistack-0.0.1.dist-info/RECORD
