Metadata-Version: 2.1
Name: aistack
Version: 0.0.1
Summary: AIStack application combines AutoGen and CrewAI or similar frameworks into a low-code solution for building and managing multi-agent LLM systems, focusing on simplicity, customization, and efficient human-agent collaboration.
Home-page: https://github.com/aistackhq/aistack
Author: Team AIStack
Author-email: team@aistack.run
Classifier: Programming Language :: Python :: 3
Classifier: Operating System :: OS Independent
Requires-Python: >=3.10
Requires-Dist: pyautogen
Requires-Dist: rich
Requires-Dist: crewai
